libjpcalc/__init__.py
libjpcalc/main.py
libjpcalc/soma/__init__.py
libjpcalc/soma/sum.py
libjpcalc/utils/__init__.py
libjpcalc/utils/utils.py
libjpcalc-0.1.2.dist-info/entry_points.txt
libjpcalc-0.1.2.dist-info/METADATA
libjpcalc-0.1.2.dist-info/WHEEL
libjpcalc-0.1.2.dist-info/RECORD
